rada_package_budzsergiy
