Metadata-Version: 1.0
Name: rada-package-BudzSergiy
Version: 0.2.dev0
Summary: Rada with abstract factory
Home-page: UNKNOWN
Author: Budz Sergiy
Author-email: UNKNOWN
License: UNKNOWN
Keywords: abstract factory python
Platform: UNKNOWN
